MANIFEST.in
README.md
setup.py
magic_square_dpp.egg-info/PKG-INFO
magic_square_dpp.egg-info/SOURCES.txt
magic_square_dpp.egg-info/dependency_links.txt
magic_square_dpp.egg-info/requires.txt
magic_square_dpp.egg-info/top_level.txt
myPackage/__init__.py
myPackage/magic_square_dpp.py