Metadata-Version: 1.0
Name: magic-square-dpp
Version: 0.1
Summary: check if matrix is magic square
Home-page: https://gitlab.com/DanielSze/dpplab10
Author: Daniel Szemik
Author-email: szemikd226195@e-science.pl
License: MIT
Platform: UNKNOWN
